{
    "name": "631973a4-ed1655d9",
    "frames": [
        {
            "timestamp": 10000,
            "objects": [
                {
                    "category": "car",
                    "id": 0,
                    "attributes": {
                        "occluded": true,
                        "truncated": false,
                        "trafficLightColor": "none"
                    },
                    "box2d": {
                        "x1": 663.884059,
                        "y1": 349.780328,
                        "x2": 681.847099,
                        "y2": 367.743368
                    }
                },
                {
                    "category": "car",
                    "id": 1,
                    "attributes": {
                        "occluded": true,
                        "truncated": false,
                        "trafficLightColor": "none"
                    },
                    "box2d": {
                        "x1": 672.86558,
                        "y1": 353.772113,
                        "x2": 696.317327,
                        "y2": 371.735154
                    }
                },
                {
                    "category": "car",
                    "id": 2,
                    "attributes": {
                        "occluded": true,
                        "truncated": false,
                        "trafficLightColor": "none"
                    },
                    "box2d": {
                        "x1": 684.341966,
                        "y1": 352.774168,
                        "x2": 724.75881,
                        "y2": 380.716676
                    }
                },
                {
                    "category": "car",
                    "id": 3,
                    "attributes": {
                        "occluded": true,
                        "truncated": false,
                        "trafficLightColor": "none"
                    },
                    "box2d": {
                        "x1": 712.783447,
                        "y1": 351.277248,
                        "x2": 762.680784,
                        "y2": 387.20333
                    }
                },
                {
                    "category": "car",
                    "id": 4,
                    "attributes": {
                        "occluded": true,
                        "truncated": false,
                        "trafficLightColor": "none"
                    },
                    "box2d": {
                        "x1": 750.705423,
                        "y1": 347.28546,
                        "x2": 811.580173,
                        "y2": 407.162264
                    }
                },
                {
                    "category": "car",
                    "id": 5,
                    "attributes": {
                        "occluded": false,
                        "truncated": false,
                        "trafficLightColor": "none"
                    },
                    "box2d": {
                        "x1": 781.1428,
                        "y1": 348.78238,
                        "x2": 897.902565,
                        "y2": 419.636598
                    }
                },
                {
                    "category": "car",
                    "id": 6,
                    "attributes": {
                        "occluded": true,
                        "truncated": false,
                        "trafficLightColor": "none"
                    },
                    "box2d": {
                        "x1": 587.042161,
                        "y1": 349.780328,
                        "x2": 603.009307,
                        "y2": 366.745422
                    }
                },
                {
                    "category": "car",
                    "id": 7,
                    "attributes": {
                        "occluded": true,
                        "truncated": false,
                        "trafficLightColor": "none"
                    },
                    "box2d": {
                        "x1": 575.565772,
                        "y1": 347.28546,
                        "x2": 592.530867,
                        "y2": 369.739262
                    }
                },
                {
                    "category": "car",
                    "id": 8,
                    "attributes": {
                        "occluded": true,
                        "truncated": false,
                        "trafficLightColor": "none"
                    },
                    "box2d": {
                        "x1": 555.107866,
                        "y1": 341.297781,
                        "x2": 579.058588,
                        "y2": 378.221811
                    }
                },
                {
                    "category": "car",
                    "id": 9,
                    "attributes": {
                        "occluded": true,
                        "truncated": false,
                        "trafficLightColor": "none"
                    },
                    "box2d": {
                        "x1": 539.140718,
                        "y1": 342.295727,
                        "x2": 573.070907,
                        "y2": 389.698196
                    }
                },
                {
                    "category": "car",
                    "id": 10,
                    "attributes": {
                        "occluded": true,
                        "truncated": false,
                        "trafficLightColor": "none"
                    },
                    "box2d": {
                        "x1": 527.664331,
                        "y1": 344.29162,
                        "x2": 561.59452,
                        "y2": 401.174584
                    }
                },
                {
                    "category": "car",
                    "id": 11,
                    "attributes": {
                        "occluded": true,
                        "truncated": false,
                        "trafficLightColor": "none"
                    },
                    "box2d": {
                        "x1": 461.799847,
                        "y1": 325.330633,
                        "x2": 544.130452,
                        "y2": 411.653025
                    }
                },
                {
                    "category": "car",
                    "id": 12,
                    "attributes": {
                        "occluded": true,
                        "truncated": false,
                        "trafficLightColor": "none"
                    },
                    "box2d": {
                        "x1": 423.378899,
                        "y1": 325.829606,
                        "x2": 528.163305,
                        "y2": 418.139678
                    }
                },
                {
                    "category": "car",
                    "id": 13,
                    "attributes": {
                        "occluded": true,
                        "truncated": false,
                        "trafficLightColor": "none"
                    },
                    "box2d": {
                        "x1": 331.567799,
                        "y1": 335.809073,
                        "x2": 513.693075,
                        "y2": 464.045227
                    }
                },
                {
                    "category": "car",
                    "id": 14,
                    "attributes": {
                        "occluded": false,
                        "truncated": false,
                        "trafficLightColor": "none"
                    },
                    "box2d": {
                        "x1": 909.16469,
                        "y1": 328.324472,
                        "x2": 1131.422098,
                        "y2": 456.657014
                    }
                },
                {
                    "category": "car",
                    "id": 15,
                    "attributes": {
                        "occluded": false,
                        "truncated": false,
                        "trafficLightColor": "none"
                    },
                    "box2d": {
                        "x1": 0,
                        "y1": 319.109721,
                        "x2": 368.145336,
                        "y2": 627.209516
                    }
                },
                {
                    "category": "car",
                    "id": 16,
                    "attributes": {
                        "occluded": false,
                        "truncated": true,
                        "trafficLightColor": "none"
                    },
                    "box2d": {
                        "x1": 1125.434418,
                        "y1": 342.794701,
                        "x2": 1279.617188,
                        "y2": 505.460017
                    }
                },
                {
                    "category": "traffic sign",
                    "id": 17,
                    "attributes": {
                        "occluded": false,
                        "truncated": false,
                        "trafficLightColor": "none"
                    },
                    "box2d": {
                        "x1": 1204.521697,
                        "y1": 184.121172,
                        "x2": 1249.429298,
                        "y2": 212.063681
                    }
                },
                {
                    "category": "area/drivable",
                    "id": 18,
                    "attributes": {},
                    "poly2d": [
                        [
                            594.569112,
                            374.624742,
                            "L"
                        ],
                        [
                            660.381568,
                            372.937244,
                            "L"
                        ],
                        [
                            1280.811618,
                            629.437067,
                            "L"
                        ],
                        [
                            959.068862,
                            619.312074,
                            "C"
                        ],
                        [
                            608.069104,
                            580.499602,
                            "C"
                        ],
                        [
                            314.533544,
                            614.809804,
                            "C"
                        ],
                        [
                            594.569112,
                            374.624742,
                            "L"
                        ]
                    ]
                }
            ]
        }
    ],
    "attributes": {
        "weather": "rainy",
        "scene": "city street",
        "timeofday": "night"
    }
}